eawrcsdk/__init__.py
eawrcsdk/eawrcsdk.py
py_eawrc_sdk-0.0.3.dist-info/licenses/LICENSE
py_eawrc_sdk-0.0.3.dist-info/METADATA
py_eawrc_sdk-0.0.3.dist-info/WHEEL
py_eawrc_sdk-0.0.3.dist-info/top_level.txt
py_eawrc_sdk-0.0.3.dist-info/RECORD
