Metadata-Version: 2.4
Name: py-eawrc-sdk
Version: 0.0.3
Summary: Python library to help aid access to EA WRC telemetry
Author-email: Josh Delima <jDelima14@gmail.com>
License-Expression: MIT
Project-URL: Homepage, https://github.com/ChequeredFox/py-eawrc-sdk/
Project-URL: Issues, https://github.com/ChequeredFox/py-eawrc-sdk/issues
Keywords: EA WRC,Telemetry,SDK
Classifier: Programming Language :: Python :: 3
Classifier: Operating System :: OS Independent
Requires-Python: >=3.9
License-File: LICENSE
Dynamic: license-file
